fourget/__init__.py
fourget/__main__.py
fourget/console.py
fourget/exception.py
fourget/log.py
fourget/queue.py
fourget-0.10.6.dist-info/entry_points.txt
fourget-0.10.6.dist-info/WHEEL
fourget-0.10.6.dist-info/METADATA
fourget-0.10.6.dist-info/RECORD
