Metadata-Version: 2.1
Name: fourget
Version: 0.10.6
Summary: Download/scrape media files from 4chan threads
Home-page: https://github.com/t-mart/fourget
License: MIT
Author: Tim Martin
Author-email: tim@timmart.in
Requires-Python: >=3.10,<4.0
Classifier: License :: OSI Approved :: MIT License
Classifier: Programming Language :: Python :: 3
Classifier: Programming Language :: Python :: 3.10
Requires-Dist: aiofiles (>=0.7.0,<0.8.0)
Requires-Dist: arrow (>=1.2.0,<2.0.0)
Requires-Dist: attrs (>=21.2.0,<22.0.0)
Requires-Dist: httpx (==1.0.0b0)
Requires-Dist: rich (>=10.16.2,<11.0.0)
Requires-Dist: tqdm (>=4.62.3,<5.0.0)
Requires-Dist: typer (>=0.4.0,<0.5.0)
Requires-Dist: yarl (>=1.7.0,<2.0.0)
Project-URL: Repository, https://github.com/t-mart/fourget
